{
  "keywords": [
    "auto", "break", "case", "char", "const", "continue", "default", "do", "double",
    "else", "enum", "extern", "float", "for", "goto", "if", "int", "long", "register",
    "return", "short", "signed", "sizeof", "static", "struct", "switch", "typedef", "union",
    "unsigned", "void", "volatile", "while", "asm", "bool", "catch", "class", "const_cast",
    "delete", "dynamic_cast", "explicit", "export", "false", "friend", "inline", "mutable",
    "namespace", "new", "operator", "private", "protected", "public", "reinterpret_cast",
    "static_cast", "template", "this", "throw", "true", "try", "typeid", "typename", "using",
    "virtual", "wchar_t", "and", "and_eq", "bitand", "bitor", "compl", "not", "not_eq",
    "or", "or_eq", "xor", "xor_eq", "nullptr", "constexpr", "decltype", "noexcept",
    "static_assert", "thread_local", "alignas", "alignof", "char16_t", "char32_t",
    "concept", "requires", "co_await", "co_yield", "co_return", "import", "module"
  ],
  "builtinFunctions": [
    { "name": "printf", "signature": "int printf(const char *format, ...)", "description": "格式化输出" },
    { "name": "scanf", "signature": "int scanf(const char *format, ...)", "description": "格式化输入" },
    { "name": "malloc", "signature": "void *malloc(size_t size)", "description": "分配内存" },
    { "name": "free", "signature": "void free(void *ptr)", "description": "释放内存" },
    { "name": "memcpy", "signature": "void *memcpy(void *dest, const void *src, size_t n)", "description": "内存复制" },
    { "name": "memset", "signature": "void *memset(void *s, int c, size_t n)", "description": "内存填充" },
    { "name": "strlen", "signature": "size_t strlen(const char *s)", "description": "字符串长度" },
    { "name": "strcpy", "signature": "char *strcpy(char *dest, const char *src)", "description": "字符串复制" },
    { "name": "strcmp", "signature": "int strcmp(const char *s1, const char *s2)", "description": "字符串比较" },
    { "name": "abs", "signature": "int abs(int j)", "description": "整数绝对值" },
    { "name": "fabs", "signature": "double fabs(double x)", "description": "浮点数绝对值" },
    { "name": "sqrt", "signature": "double sqrt(double x)", "description": "平方根" },
    { "name": "pow", "signature": "double pow(double x, double y)", "description": "幂运算" },
    { "name": "sin", "signature": "double sin(double x)", "description": "正弦函数" },
    { "name": "cos", "signature": "double cos(double x)", "description": "余弦函数" },
    { "name": "tan", "signature": "double tan(double x)", "description": "正切函数" },
    { "name": "exp", "signature": "double exp(double x)", "description": "自然指数" },
    { "name": "log", "signature": "double log(double x)", "description": "自然对数" },
    { "name": "rand", "signature": "int rand(void)", "description": "随机数生成" },
    { "name": "srand", "signature": "void srand(unsigned int seed)", "description": "设置随机数种子" },
    { "name": "time", "signature": "time_t time(time_t *tloc)", "description": "获取系统时间" },
    { "name": "exit", "signature": "void exit(int status)", "description": "退出程序" },
    { "name": "cin", "signature": "extern istream cin", "description": "标准输入流" },
    { "name": "cout", "signature": "extern ostream cout", "description": "标准输出流" },
    { "name": "cerr", "signature": "extern ostream cerr", "description": "标准错误流" },
    { "name": "clog", "signature": "extern ostream clog", "description": "标准日志流" },
    { "name": "endl", "signature": "template<typename T> basic_ostream<T>& endl(basic_ostream<T>& os)", "description": "换行并刷新缓冲区" },
    { "name": "ends", "signature": "template<typename T> basic_ostream<T>& ends(basic_ostream<T>& os)", "description": "插入空字符" },
    { "name": "flush", "signature": "template<typename T> basic_ostream<T>& flush(basic_ostream<T>& os)", "description": "刷新流" },
    { "name": "boolalpha", "signature": "ios_base& boolalpha(ios_base& str)", "description": "以文字形式显示布尔值" },
    { "name": "noboolalpha", "signature": "ios_base& noboolalpha(ios_base& str)", "description": "以数字形式显示布尔值" },
    { "name": "dec", "signature": "ios_base& dec(ios_base& str)", "description": "十进制" },
    { "name": "hex", "signature": "ios_base& hex(ios_base& str)", "description": "十六进制" },
    { "name": "oct", "signature": "ios_base& oct(ios_base& str)", "description": "八进制" },
    { "name": "fixed", "signature": "ios_base& fixed(ios_base& str)", "description": "固定点表示" },
    { "name": "scientific", "signature": "ios_base& scientific(ios_base& str)", "description": "科学计数法" },
    { "name": "left", "signature": "ios_base& left(ios_base& str)", "description": "左对齐" },
    { "name": "right", "signature": "ios_base& right(ios_base& str)", "description": "右对齐" },
    { "name": "setw", "signature": "/*unspecified*/ setw(int n)", "description": "设置宽度" },
    { "name": "setfill", "signature": "/*unspecified*/ setfill(char_type c)", "description": "设置填充字符" },
    { "name": "setprecision", "signature": "/*unspecified*/ setprecision(int n)", "description": "设置精度" },
    { "name": "stringstream", "signature": "typedef basic_stringstream<char> stringstream", "description": "字符串流" },
    { "name": "istringstream", "signature": "typedef basic_istringstream<char> istringstream", "description": "输入字符串流" },
    { "name": "ostringstream", "signature": "typedef basic_ostringstream<char> ostringstream", "description": "输出字符串流" }
  ],
  "standardLibraries": [
    "iostream", "fstream", "sstream", "string", "vector", "list", "deque", "array",
    "forward_list", "set", "multiset", "map", "multimap", "unordered_set", "unordered_map",
    "unordered_multiset", "unordered_multimap", "stack", "queue", "priority_queue",
    "bitset", "valarray", "algorithm", "numeric", "functional", "iterator", "memory",
    "memory_resource", "scoped_allocator", "utility", "tuple", "type_traits", "ratio",
    "chrono", "ctime", "random", "complex", "valarray", "numeric_limits", "limits",
    "exception", "stdexcept", "cassert", "cerrno", "cctype", "cwctype", "cstring",
    "cwchar", "cstdlib", "cmath", "cfenv", "csetjmp", "csignal", "cstdarg", "cstddef",
    "cstdint", "cinttypes", "climits", "cfloat", "locale", "clocale", "codecvt",
    "regex", "filesystem", "system_error", "thread", "mutex", "shared_mutex", "future",
    "condition_variable", "atomic", "barrier", "latch", "semaphore", "stop_token",
    "coroutine", "generator", "syncstream", "span", "mdspan", "format", "print",
    "expected", "optional", "variant", "any", "source_location", "bit", "numbers",
    "ranges", "views", "execution", "compare", "concepts", "contract", "modules"
  ],
  "thirdPartyLibraries": [
    "boost/version.hpp", "boost/config.hpp", "boost/lexical_cast.hpp", "boost/format.hpp",
    "boost/algorithm/string.hpp", "boost/date_time.hpp", "boost/filesystem.hpp",
    "boost/regex.hpp", "boost/uuid/uuid.hpp", "boost/thread.hpp", "boost/asio.hpp",
    "boost/bind.hpp", "boost/function.hpp", "boost/signals2.hpp", "boost/property_tree/ptree.hpp",
    "boost/program_options.hpp", "boost/serialization.hpp", "boost/graph.hpp",
    "boost/numeric/ublas.hpp", "boost/spirit.hpp", "boost/phoenix.hpp",
    "GLFW/glfw3.h", "GL/glew.h", "GL/glut.h", "glad/glad.h", "glm/glm.hpp",
    "SDL2/SDL.h", "SDL2/SDL_image.h", "SDL2/SDL_ttf.h", "SDL2/SDL_mixer.h",
    "SFML/Graphics.hpp", "SFML/Window.hpp", "SFML/System.hpp", "SFML/Audio.hpp", "SFML/Network.hpp",
    "QtWidgets/QApplication", "QtWidgets/QWidget", "QtWidgets/QLabel", "QtWidgets/QPushButton",
    "QtCore/QString", "QtCore/QTimer", "QtCore/QObject", "QtCore/QList",
    "opencv2/opencv.hpp", "opencv2/core/core.hpp", "opencv2/highgui/highgui.hpp",
    "opencv2/imgproc/imgproc.hpp", "opencv2/objdetect/objdetect.hpp",
    "eigen3/Eigen/Dense", "eigen3/Eigen/Eigenvalues", "eigen3/Eigen/Sparse",
    "armadillo", "mlpack/core.hpp", "mlpack/methods/neighbor_search/neighbor_search.hpp",
    "tensorflow/c/c_api.h", "tensorflow/cc/client/client_session.h", "tensorflow/cc/ops/standard_ops.h",
    "onnxruntime_cxx_api.h", "libtorch/torch.h", "libtorch/torch/nn.h",
    "caffe/caffe.hpp", "mxnet-cpp/MxNetCpp.h", "cntk/api/CNTKLibrary.h",
    "cuda_runtime.h", "cuda.h", "curand_kernel.h", "thrust/device_ptr.h",
    "thrust/device_vector.h", "thrust/host_vector.h", "cublas_v2.h", "cudnn.h",
    "CL/cl.h", "CL/cl2.hpp", "CL/opencl.hpp", "vulkan/vulkan.h", "vulkan/vulkan.hpp",
    "directx.h", "d3d11.h", "d3d12.h", "dxgi.h", "d3dcompiler.h",
    "curl/curl.h", "openssl/ssl.h", "openssl/crypto.h", "zlib.h", "libpng/png.h",
    "jpeglib.h", "turbojpeg.h", "webp/decode.h", "webp/encode.h",
    "sqlite3.h", "mysql/mysql.h", "postgresql/libpq-fe.h", "hiredis/hiredis.h",
    "mongoc/mongoc.h", "bson/bson.h", "leveldb/db.h", "rocksdb/db.h",
    "spdlog/spdlog.h", "fmt/core.h", "fmt/format.h", "nlohmann/json.hpp",
    "jsoncons/json.hpp", "rapidjson/document.h", "yaml-cpp/yaml.h",
    "protobuf-c/protobuf-c.h", "google/protobuf/message.h", "flatbuffers/flatbuffers.h",
    "capnp/capnp.h", "msgpack.hpp", "cereal/cereal.hpp",
    "gtest/gtest.h", "catch2/catch_test_macros.hpp", "doctest/doctest.h",
    "benchmark/benchmark.h", "tbb/tbb.h", "ppl.h", "concurrent_queue.h",
    "libuv.h", "ev.h", "event2/event.h", "asio.hpp", "restinio/all.hpp",
    "oatpp/core/macro/component.hpp", "drogon/drogon.h", "pistache/router.h",
    "crow.h", "cinatra.hpp", "libwebsockets.h", "ixwebsocket/IXWebSocket.h",
    "grpc++/grpc++.h", "grpcpp/grpcpp.h", "thrift/Thrift.h", "thrift/protocol/TBinaryProtocol.h",
    "libxml/parser.h", "libxml/tree.h", "libxml/xpath.h", "tinyxml2.h", "pugixml.hpp",
    "hpdf.h", "poppler/cpp/poppler-document.h", "podofo/podofo.h",
    "hdf5.h", "netcdf.h", "fitsio.h", "root/Rtypes.h", "root/TFile.h",
    "FLAC/all.h", "sndfile.h", "portaudio.h", "RtAudio.h", "kiss_fft.h",
    "fftw3.h", "libavcodec/avcodec.h", "libavformat/avformat.h", "libavutil/avutil.h",
    "libswscale/swscale.h", "libavfilter/avfilter.h", "liveMedia/liveMedia.hh",
    "Box2D/Box2D.h", "chipmunk/chipmunk.h", "bullet/btBulletDynamicsCommon.h",
    "ode/ode.h", "newton/Newton.h", "physx/PxPhysicsAPI.h", "jolt/Jolt.h",
    "OpenAL/al.h", "OpenAL/alc.h", "sndio.h", "alsa/asoundlib.h",
    "miniaudio.h", "dr_wav.h", "dr_flac.h", "dr_mp3.h", "stb_image.h",
    "stb_image_write.h", "stb_truetype.h", "stb_ds.h", "stb.h",
    "imgui.h", "imgui_impl_glfw.h", "imgui_impl_opengl3.h", "raylib.h",
    "allegro5/allegro.h", "love2d/love.h", "godot_cpp/godot.hpp",
    "flecs.h", "entt/entt.hpp", "EnTT/entt.hpp", "sol2/sol.hpp",
    "lua.hpp", "lauxlib.h", "lualib.h", "Python.h", "jni.h", "ruby.h",
    "duktape.h", "v8.h", "JavaScriptCore/JSBase.h", "quickjs.h",
    "wren.hpp", "chaiscript/chaiscript.hpp", "angelscript.h", "squirrel.h",
    "ncurses.h", "curses.h", "readline/readline.h", "termbox.h",
    "FT2Build.h", "freetype/freetype.h", "harfbuzz/hb.h", "cairo/cairo.h",
    "pango/pango.h", "librsvg/rsvg.h", "magick/Magick++.h",
    "gmp.h", "mpfr.h", "mpc.h", "flint/flint.h", "ntl/ZZ.h", "sodium.h",
    "libsodium.h", "bcrypt.h", "argon2.h", "srtp2/srtp.h", "libsrtp2/srtp.h"
  ],
  "stlClasses": [
    "string", "vector", "list", "deque", "array",
    "forward_list", "set", "multiset", "map", "multimap",
    "unordered_set", "unordered_map", "unordered_multiset", "unordered_multimap",
    "stack", "queue", "priority_queue", "bitset", "valarray",
    "tuple", "pair", "optional", "variant", "any",
    "function", "bind", "mem_fn", "reference_wrapper",
    "unique_ptr", "shared_ptr", "weak_ptr", "auto_ptr",
    "allocator", "scoped_allocator_adaptor", "polymorphic_allocator",
    "iterator", "reverse_iterator", "back_insert_iterator",
    "front_insert_iterator", "insert_iterator", "move_iterator",
    "istream_iterator", "ostream_iterator", "istreambuf_iterator",
    "ostreambuf_iterator", "regex_iterator", "regex_token_iterator",
    "thread", "mutex", "recursive_mutex", "timed_mutex",
    "recursive_timed_mutex", "shared_mutex", "shared_timed_mutex",
    "lock_guard", "unique_lock", "shared_lock", "scoped_lock",
    "condition_variable", "condition_variable_any", "future",
    "shared_future", "promise", "packaged_task", "async",
    "atomic", "atomic_flag", "atomic_bool", "atomic_char",
    "atomic_schar", "atomic_uchar", "atomic_short", "atomic_ushort",
    "atomic_int", "atomic_uint", "atomic_long", "atomic_ulong",
    "atomic_llong", "atomic_ullong", "atomic_char16_t", "atomic_char32_t",
    "atomic_wchar_t", "atomic_int8_t", "atomic_uint8_t", "atomic_int16_t",
    "atomic_uint16_t", "atomic_int32_t", "atomic_uint32_t", "atomic_int64_t",
    "atomic_uint64_t", "atomic_intptr_t", "atomic_uintptr_t",
    "atomic_size_t", "atomic_ptrdiff_t", "barrier", "latch",
    "counting_semaphore", "binary_semaphore", "stop_token",
    "stop_source", "stop_callback", "coroutine_handle",
    "suspend_always", "suspend_never", "generator",
    "format_context", "basic_format_args", "basic_format_string",
    "expected", "unexpected", "span", "mdspan",
    "ranges::range", "ranges::view", "ranges::take_view",
    "ranges::drop_view", "ranges::filter_view", "ranges::transform_view",
    "ranges::reverse_view", "ranges::split_view", "ranges::join_view",
    "ranges::zip_view", "ranges::chunk_view", "ranges::slide_view",
    "ranges::stride_view", "ranges::common_view", "ranges::views::all",
    "ranges::views::filter", "ranges::views::transform", "ranges::views::take",
    "ranges::views::drop", "ranges::views::reverse", "ranges::views::split",
    "ranges::views::join", "ranges::views::zip", "execution::seq",
    "execution::par", "execution::par_unseq", "execution::unseq"
  ],
  "stlMethods": [
    { "name": "begin", "signature": "iterator begin() noexcept", "description": "返回容器第一个元素的迭代器" },
    { "name": "end", "signature": "iterator end() noexcept", "description": "返回容器末尾的迭代器" },
    { "name": "cbegin", "signature": "const_iterator cbegin() const noexcept", "description": "返回容器第一个元素的const迭代器" },
    { "name": "cend", "signature": "const_iterator cend() const noexcept", "description": "返回容器末尾的const迭代器" },
    { "name": "rbegin", "signature": "reverse_iterator rbegin() noexcept", "description": "返回反向容器第一个元素的迭代器" },
    { "name": "rend", "signature": "reverse_iterator rend() noexcept", "description": "返回反向容器末尾的迭代器" },
    { "name": "crbegin", "signature": "const_reverse_iterator crbegin() const noexcept", "description": "返回反向容器第一个元素的const迭代器" },
    { "name": "crend", "signature": "const_reverse_iterator crend() const noexcept", "description": "返回反向容器末尾的const迭代器" },
    { "name": "size", "signature": "size_type size() const noexcept", "description": "返回容器中元素的数量" },
    { "name": "max_size", "signature": "size_type max_size() const noexcept", "description": "返回容器能容纳的最大元素数量" },
    { "name": "empty", "signature": "bool empty() const noexcept", "description": "检查容器是否为空" },
    { "name": "capacity", "signature": "size_type capacity() const noexcept", "description": "返回容器当前分配的存储空间大小" },
    { "name": "reserve", "signature": "void reserve(size_type n)", "description": "预留存储空间" },
    { "name": "shrink_to_fit", "signature": "void shrink_to_fit()", "description": "释放未使用的存储空间" },
    { "name": "clear", "signature": "void clear() noexcept", "description": "清空容器" },
    { "name": "insert", "signature": "iterator insert(const_iterator pos, const value_type& val)", "description": "在指定位置插入元素" },
    { "name": "erase", "signature": "iterator erase(const_iterator pos)", "description": "删除指定位置的元素" },
    { "name": "push_back", "signature": "void push_back(const value_type& val)", "description": "在容器末尾添加元素" },
    { "name": "pop_back", "signature": "void pop_back()", "description": "删除容器末尾的元素" },
    { "name": "push_front", "signature": "void push_front(const value_type& val)", "description": "在容器开头添加元素" },
    { "name": "pop_front", "signature": "void pop_front()", "description": "删除容器开头的元素" },
    { "name": "swap", "signature": "void swap(container& other) noexcept", "description": "交换两个容器的内容" },
    { "name": "front", "signature": "reference front()", "description": "访问第一个元素" },
    { "name": "back", "signature": "reference back()", "description": "访问最后一个元素" },
    { "name": "at", "signature": "reference at(size_type n)", "description": "访问指定位置的元素（带边界检查）" },
    { "name": "data", "signature": "value_type* data() noexcept", "description": "返回指向容器数据的指针" },
    { "name": "assign", "signature": "void assign(size_type n, const value_type& val)", "description": "给容器赋值" },
    { "name": "resize", "signature": "void resize(size_type n, const value_type& val)", "description": "调整容器大小" },
    { "name": "emplace", "signature": "template<class... Args> iterator emplace(const_iterator pos, Args&&... args)", "description": "在指定位置构造元素" },
    { "name": "emplace_back", "signature": "template<class... Args> reference emplace_back(Args&&... args)", "description": "在末尾构造元素" },
    { "name": "emplace_front", "signature": "template<class... Args> reference emplace_front(Args&&... args)", "description": "在开头构造元素" },
    { "name": "find", "signature": "const_iterator find(const key_type& k) const", "description": "查找指定键的元素" },
    { "name": "count", "signature": "size_type count(const key_type& k) const", "description": "计算指定键的元素数量" },
    { "name": "lower_bound", "signature": "iterator lower_bound(const key_type& k)", "description": "返回第一个不小于给定键的元素" },
    { "name": "upper_bound", "signature": "iterator upper_bound(const key_type& k)", "description": "返回第一个大于给定键的元素" },
    { "name": "equal_range", "signature": "pair<iterator,iterator> equal_range(const key_type& k)", "description": "返回匹配给定键的元素范围" },
    { "name": "append", "signature": "string& append(const string& str)", "description": "在字符串末尾添加内容" },
    { "name": "substr", "signature": "string substr(size_t pos = 0, size_t len = npos) const", "description": "获取子字符串" },
    { "name": "c_str", "signature": "const char* c_str() const noexcept", "description": "返回C风格字符串" },
    { "name": "length", "signature": "size_type length() const noexcept", "description": "返回字符串长度" },
    { "name": "compare", "signature": "int compare(const string& str) const noexcept", "description": "比较字符串" },
    { "name": "replace", "signature": "string& replace(size_t pos, size_t len, const string& str)", "description": "替换字符串" },
    { "name": "find", "signature": "size_t find(const string& str, size_t pos = 0) const noexcept", "description": "查找子字符串" },
    { "name": "rfind", "signature": "size_t rfind(const string& str, size_t pos = npos) const noexcept", "description": "反向查找子字符串" },
    { "name": "get", "signature": "T& get()", "description": "获取智能指针的内容" },
    { "name": "reset", "signature": "void reset(pointer p = pointer()) noexcept", "description": "重置智能指针" },
    { "name": "release", "signature": "pointer release() noexcept", "description": "释放智能指针的所有权" },
    { "name": "use_count", "signature": "long use_count() const noexcept", "description": "返回shared_ptr的引用计数" },
    { "name": "unique", "signature": "bool unique() const noexcept", "description": "检查是否是唯一的所有者" },
    { "name": "lock", "signature": "void lock()", "description": "锁定互斥锁" },
    { "name": "unlock", "signature": "void unlock()", "description": "解锁互斥锁" },
    { "name": "try_lock", "signature": "bool try_lock()", "description": "尝试锁定互斥锁" },
    { "name": "join", "signature": "void join()", "description": "等待线程完成" },
    { "name": "detach", "signature": "void detach()", "description": "分离线程" },
    { "name": "joinable", "signature": "bool joinable() const noexcept", "description": "检查线程是否可加入" },
    { "name": "get_id", "signature": "id get_id() const noexcept", "description": "获取线程ID" },
    { "name": "get", "signature": "T get()", "description": "获取future的结果" },
    { "name": "valid", "signature": "bool valid() const noexcept", "description": "检查future是否有效" },
    { "name": "wait", "signature": "void wait() const", "description": "等待结果" },
    { "name": "wait_for", "signature": "template<class Rep, class Period> future_status wait_for(const chrono::duration<Rep,Period>& rel_time) const", "description": "等待结果一段时间" },
    { "name": "set_value", "signature": "void set_value(const R& value)", "description": "设置promise的值" },
    { "name": "set_exception", "signature": "void set_exception(exception_ptr p)", "description": "设置promise的异常" }
  ]
}
